LICENSE
MANIFEST.in
README.rst
requirements.txt
setup.py
amulog/__init__.py
amulog/__main__.py
amulog/anonymize.py
amulog/cli.py
amulog/common.py
amulog/config.py
amulog/db_common.py
amulog/db_mysql.py
amulog/db_sqlite.py
amulog/host_alias.py
amulog/log_db.py
amulog/logparser.py
amulog/lt_common.py
amulog/lt_import.py
amulog/lt_import_ext.py
amulog/lt_label.py
amulog/lt_misc.py
amulog/lt_regex.py
amulog/lt_search.py
amulog/lt_va.py
amulog/ltg_semantics.py
amulog/manager.py
amulog/mproc_queue.py
amulog/strutil.py
amulog/testutil.py
amulog.egg-info/PKG-INFO
amulog.egg-info/SOURCES.txt
amulog.egg-info/dependency_links.txt
amulog.egg-info/entry_points.txt
amulog.egg-info/requires.txt
amulog.egg-info/top_level.txt
amulog/alg/__init__.py
amulog/alg/meta.py
amulog/alg/crf/__init__.py
amulog/alg/crf/__main__.py
amulog/alg/crf/_convert.py
amulog/alg/crf/_items.py
amulog/alg/crf/lt_crf.py
amulog/alg/crf/train.py
amulog/alg/dlog/__init__.py
amulog/alg/dlog/dlog.py
amulog/alg/drain/__init__.py
amulog/alg/drain/drain.py
amulog/alg/fttree/__init__.py
amulog/alg/fttree/fttree.py
amulog/alg/lenma/__init__.py
amulog/alg/lenma/lenma.py
amulog/alg/shiso/__init__.py
amulog/alg/shiso/shiso.py
amulog/data/config.conf.default
amulog/data/crf_template.default
amulog/data/crf_template.sample
amulog/data/drain_regex.conf
amulog/data/host_alias.txt.sample
amulog/data/lt_label.conf.sample
amulog/data/testlog.conf
amulog/edit/__init__.py
amulog/edit/__main__.py
amulog/edit/lt_tool.py
amulog/edit/search.py
amulog/eval/__init__.py
amulog/eval/__main__.py
amulog/eval/cluster_metrics.py
amulog/eval/maketpl.py
amulog/eval/param_searcher.py
amulog/eval/structure_metrics.py
amulog/external/__init__.py
amulog/external/mod_tplseq.py
amulog/external/regexhash.py
amulog/external/tpl_match.py
tests/__init__.py
tests/test_crf.py
tests/test_db.py
tests/test_ltgen.py
tests-ext/__init__.py
tests-ext/test_mysql.py