Metadata-Version: 2.1
Name: amulog
Version: 0.3.3
Summary: A system log management tool with automatically generated log templates.
Home-page: https://github.com/cpflat/amulog/
Author: Satoru Kobayashi
Author-email: sat@nii.ac.jp
License: The 3-Clause BSD License
Platform: UNKNOWN
Classifier: Development Status :: 4 - Beta
Classifier: Environment :: Console
Classifier: Intended Audience :: Information Technology
Classifier: Intended Audience :: Science/Research
Classifier: Intended Audience :: Developers
Classifier: License :: OSI Approved :: BSD License
Classifier: Operating System :: OS Independent
Classifier: Programming Language :: Python :: 3.7
Classifier: Topic :: Scientific/Engineering :: Information Analysis
Classifier: Topic :: Software Development :: Libraries :: Python Modules
License-File: LICENSE
